<?xml version="1.0" encoding="UTF-8"?><?xml-stylesheet type='text/xsl' href='_UpgradeReport_Files/UpgradeReport.xslt'?><UpgradeLog>
<Properties><Property Name="Solution" Value="stdshader_dx9-2010">
</Property><Property Name="Solution File" Value="C:\city17_source\SourceCode\source\src\materialsystem\stdshaders\stdshader_dx9-2010.sln">
</Property><Property Name="Date" Value="Friday, June 04, 2010">
</Property><Property Name="Time" Value="18:59:07 PM">
</Property><Property Name="Log Number" Value="5">
</Property></Properties><Event ErrorLevel="3" Project="stdshader_dx9-2010" Source="stdshader_dx9-2010.vcproj" Description="No Conversion Required">
</Event></UpgradeLog>